[{"level1":"1","floor":"1","level2":"2"},{"level1":"3","floor":"2","level2":"4"},{"level1":"5","floor":"3","level2":"8"},{"level1":"9","floor":"4","level2":"13"},{"level1":"14","floor":"5","level2":"19"},{"level1":"20","floor":"6","level2":"25"},{"level1":"26","floor":"7","level2":"30"},{"level1":"31","floor":"8","level2":"40"},{"level1":"41","floor":"9","level2":"50"},{"level1":"51","floor":"10","level2":"60"},{"level1":"61","floor":"11","level2":"70"},{"level1":"71","floor":"11","level2":"80"},{"level1":"81","floor":"12","level2":"90"},{"level1":"91","floor":"12","level2":"100"},{"level1":"101","floor":"13","level2":"115"},{"level1":"116","floor":"13","level2":"130"},{"level1":"131","floor":"14","level2":"145"},{"level1":"146","floor":"14","level2":"160"},{"level1":"161","floor":"15","level2":"175"},{"level1":"176","floor":"16","level2":"9999999999"}]